flitch/__init__.py
flitch/splitter.py
flitch/utils.py
flitch-0.1.3.dist-info/LICENSE
flitch-0.1.3.dist-info/WHEEL
flitch-0.1.3.dist-info/METADATA
flitch-0.1.3.dist-info/RECORD
