Metadata-Version: 2.1
Name: flitch
Version: 0.1.3
Summary: A simple text file splitting utility
Home-page: https://github.com/python-poetry/poetry
License: MIT
Keywords: simple,utility,text,splitting
Author: Altynbek Orumbayev
Author-email: aorumbayev@protonmail.com
Requires-Python: >=3.6,<4.0
Classifier: License :: OSI Approved :: MIT License
Classifier: Programming Language :: Python :: 3
Classifier: Programming Language :: Python :: 3.6
Classifier: Programming Language :: Python :: 3.7
Classifier: Programming Language :: Python :: 3.8
Project-URL: Repository, https://github.com/python-poetry/poetry
